{
  "version": 3,
  "middleware": {
    "/": {
      "files": [
        "server/edge/chunks/_ae847000._.js",
        "server/edge/chunks/[root-of-the-server]__8978dbac._.js",
        "server/edge/chunks/turbopack-edge-wrapper_611be750.js"
      ],
      "name": "middleware",
      "page": "/",
      "matchers": [
        {
          "regexp": "^(?:\\/(_next\\/data\\/[^/]{1,}))?(?:\\/((?!_next\\/static|_next\\/image|favicon.ico|.*\\.(?:svg|png|jpg|jpeg|gif|webp|css|js)$).*))(\\\\.json)?[\\/#\\?]?$",
          "originalSource": "/((?!_next/static|_next/image|favicon.ico|.*\\.(?:svg|png|jpg|jpeg|gif|webp|css|js)$).*)"
        }
      ],
      "wasm": [],
      "assets": [],
      "env": {
        "__NEXT_BUILD_ID": "development",
        "NEXT_SERVER_ACTIONS_ENCRYPTION_KEY": "+xdDwTjxP0q7/zccDKtYRlZNpLTQXl+VFoOlo02kpow=",
        "__NEXT_PREVIEW_MODE_ID": "c459537855de06a6aa661e34229fc37c",
        "__NEXT_PREVIEW_MODE_ENCRYPTION_KEY": "02071986786c044414ef8c29ff0e957ed88aec8a6a1f6b8d1532dae51ac4c0e8",
        "__NEXT_PREVIEW_MODE_SIGNING_KEY": "334dbfe4f790820f50c9c2141e482a65cb2e0e00a89bf1d6358362ebf8d1967a"
      }
    }
  },
  "sortedMiddleware": [
    "/"
  ],
  "functions": {}
}